{
    "24001": "Vorpal Blade",
    "24003": "Corruptive Flames",
    "24004": "Divine Blessing",
    "24005": "Waspomancy",
    "24008": "Divine Might",
    "24009": "Divine Ward",
    "24012": "Call of the Wild",
    "24016": "Heavenly Thunder",
    "24017": "Echo of Zhu Youjian",
    "24019": "Ethereal Form",
    "24029": "Lotus Lantern",
    "24030": "Burning Flames",
    "24031": "Infernal Flames",
    "24032": "Darkfrost Flames",
    "24034": "Cinder Incantation",
    "24035": "Lotus Soulflame",
    "24041": "Crimson Edge Incantation",
    "24043": "Aurum Feather Force",
    "24045": "Echo of Xuanyangzi",
    "24049": "Demonbane Strike",
    "24054": "Thunderstorm",
    "24055": "Echo of the Great Centipede",
    "24057": "Echo of Honglan",
    "24058": "Echo of Lu Bingzhang",
    "24059": "Echo of Soulwood",
    "24060": "Echo of Liu Cheng'en",
    "24061": "Plume Vortex",
    "24062": "Echo of Fang Ling",
    "24063": "Echo of Dhutanga",
    "24064": "Spiritual Flames",
    "24066": "Echo of Ai Nengqi",
    "24069": "Echo of Lu Hongliu",
    "24070": "Echo of Bai Kru",
    "24071": "Echo of Huang Yan",
    "24072": "Echo of Zhang Xianzhong",
    "24073": "Echo of Zhao Yun",
    "24077": "Polygonal Container",
    "24078": "Echo of the Bo Magus",
    "24081": "Echo of the Bo Sorcerer"
}
